AUTHORS
LICENSE
MANIFEST.in
README.rst
setup.py
pinax/__init__.py
pinax/boxes/__init__.py
pinax/boxes/admin.py
pinax/boxes/conf.py
pinax/boxes/forms.py
pinax/boxes/hooks.py
pinax/boxes/models.py
pinax/boxes/urls.py
pinax/boxes/views.py
pinax/boxes/migrations/0001_initial.py
pinax/boxes/migrations/0002_box_content_html.py
pinax/boxes/migrations/__init__.py
pinax/boxes/templatetags/__init__.py
pinax/boxes/templatetags/pinax_boxes_tags.py
pinax/boxes/tests/__init__.py
pinax/boxes/tests/models.py
pinax/boxes/tests/tests.py
pinax/boxes/tests/urls.py
pinax_boxes.egg-info/PKG-INFO
pinax_boxes.egg-info/SOURCES.txt
pinax_boxes.egg-info/dependency_links.txt
pinax_boxes.egg-info/not-zip-safe
pinax_boxes.egg-info/requires.txt
pinax_boxes.egg-info/top_level.txt