Metadata-Version: 1.1
Name: pinax-boxes
Version: 3.0.0
Summary: An app for including boxes of admin-controllable content in templates.
Home-page: http://github.com/pinax/pinax-boxes/
Author: Pinax Team
Author-email: developers@pinaxproject.com
License: MIT
Platform: UNKNOWN
Classifier: Development Status :: 5 - Production/Stable
Classifier: Environment :: Web Environment
Classifier: Framework :: Django
Classifier: Intended Audience :: Developers
Classifier: License :: OSI Approved :: MIT License
Classifier: Operating System :: OS Independent
Classifier: Programming Language :: Python
Classifier: Programming Language :: Python :: 2
Classifier: Programming Language :: Python :: 3
Classifier: Topic :: Software Development :: Libraries :: Python Modules
